gitscrap/__init__.py
gitscrap/__main__.py
gitscrap/api.py
gitscrap/helpers.py
gitscrap/main.py
gitscrap/py.typed
gitscrap/scrapers.py
gitscrap/type.py
gitscrap-1.0.1.dist-info/LICENSE
gitscrap-1.0.1.dist-info/METADATA
gitscrap-1.0.1.dist-info/WHEEL
gitscrap-1.0.1.dist-info/entry_points.txt
gitscrap-1.0.1.dist-info/RECORD
