Metadata-Version: 2.1
Name: gitscrap
Version: 1.0.1
Summary: Scrap emails from Github repositories
Home-page: https://caross.io/
License: MIT
Author: Antoine Carossio
Author-email: antoine.carossio@me.com
Maintainer: Antoine Carossio
Maintainer-email: antoine.carossio@me.com
Requires-Python: >=3.9,<=3.12
Classifier: License :: OSI Approved :: MIT License
Classifier: Programming Language :: Python :: 3
Classifier: Programming Language :: Python :: 3.9
Classifier: Programming Language :: Python :: 3.10
Classifier: Programming Language :: Python :: 3.11
Requires-Dist: requests (>=2.31.0,<3.0.0)
Project-URL: Repository, https://github.com/iCarossio/GitScrap
